{"type": "Feature", "id": 12517844, "geometry": {"type": "Point", "coordinates": [-71.198303, 21.3223]}, "properties": {"woe:id": 12517844, "woe:parent_id": 162156, "woe:name": "Salt Cay Airport", "woe:placetype": 14, "woe:placetype_name": "Airport", "woe:lang": "ENG", "iso:country": "TC", "meta:provider": ["geoplanet:7.3.1", "geoplanet:7.3.2", "geoplanet:7.4.0", "geoplanet:7.4.1", "geoplanet:7.5.1", "geoplanet:7.5.2", "geoplanet:7.6.0", "geoplanet:7.8.1", "geoplanet:7.9.0", "geoplanet:7.10.0", "geoplanet:8.0.0", "woeplanet:8.0.0"], "meta:indexed": "2020-08-20T20:56:33.178355", "woe:alias_ENG_V": ["SLX Airport", "SLX"], "meta:updated": "2020-10-14T11:23:07.151459", "woe:hierarchy": {"continent": 24865672, "country": 23424962, "town": 0, "planet": 1, "county": 0, "suburb": 0, "state": 24549930, "region": 0, "localadmin": 0}, "woe:timezone_id": 28350758, "woe:hash": "d7v37cdgrkc3", "woe:centroid": [-71.198303, 21.3223], "geom:latitude": 21.3223, "geom:longitude": -71.198303, "geom:hash": "d7v37cdgrkc3", "woe:latitude": 21.3223, "geom:centroid": [-71.198303, 21.3223], "woe:longitude": -71.198303, "woe:repo": "woeplanet-airport-tc", "geom:area": 0.0, "woe:scale": 19}}